LICENSE
README.md
setup.py
kudos/__init__.py
kudos/inference.py
kudos/metrics.py
kudos/optimizers.py
kudos/tools.py
kudos.egg-info/PKG-INFO
kudos.egg-info/SOURCES.txt
kudos.egg-info/dependency_links.txt
kudos.egg-info/requires.txt
kudos.egg-info/top_level.txt