Metadata-Version: 2.1
Name: kudos
Version: 0.0.1
Summary: Tools for optimizing public health case definitions
Home-page: https://github.com/scotthlee/kudos
Author: Scott Lee
Author-email: yle4@cdc.gov
License: Apache 2.0
Keywords: combinatorial optimization
Platform: UNKNOWN
Classifier: Development Status :: 2 - Pre-Alpha
Classifier: Programming Language :: Python :: 3.8
Classifier: Programming Language :: Python :: 3.9
License-File: LICENSE
